dgus/__init__.py
dgus/_version.py
dgus/config_sanity_check.py
dgus/icl_helper.py
dgus/display/__init__.py
dgus/display/dgus_logger.py
dgus/display/display.py
dgus/display/mask.py
dgus/display/onscreen_keyboard.py
dgus/display/communication/__init__.py
dgus/display/communication/communication_interface.py
dgus/display/communication/dgus_cmd.py
dgus/display/communication/protocol.py
dgus/display/communication/request.py
dgus/display/controls/__init__.py
dgus/display/controls/control.py
dgus/display/controls/data_variable.py
dgus/display/controls/text_variable.py
dgus/display/serialization/__init__.py
dgus/display/serialization/json_serializable.py
sample/__init__.py
sample/main.py
sample/overview_display_mask.py
tests/__init__.py
tests/test_communication_interface.py
tests/test_control.py
tests/test_data_variable.py
tests/test_mask.py
tests/test_protocol.py
tests/test_text_variable.py
libdgus-0.1.6.dist-info/METADATA
libdgus-0.1.6.dist-info/WHEEL
libdgus-0.1.6.dist-info/top_level.txt
libdgus-0.1.6.dist-info/RECORD
