Metadata-Version: 2.1
Name: libdgus
Version: 0.1.6
Home-page: https://github.com/seho85/python-dgus
Maintainer: seho85
License: GPLv3
Project-URL: Bug Tracker, https://github.com/seho85/python-dgus/issues
Requires-Dist: pyserial
